trytond/modules/health_lifestyle/COPYING
trytond/modules/health_lifestyle/README.rst
trytond/modules/health_lifestyle/__init__.py
trytond/modules/health_lifestyle/data/diets_beliefs.xml
trytond/modules/health_lifestyle/data/recreational_drugs.xml
trytond/modules/health_lifestyle/data/vegetarian_types.xml
trytond/modules/health_lifestyle/health_lifestyle.py
trytond/modules/health_lifestyle/health_lifestyle_view.xml
trytond/modules/health_lifestyle/locale/ar.po
trytond/modules/health_lifestyle/locale/de.po
trytond/modules/health_lifestyle/locale/el.po
trytond/modules/health_lifestyle/locale/eo.po
trytond/modules/health_lifestyle/locale/es.po
trytond/modules/health_lifestyle/locale/fr.po
trytond/modules/health_lifestyle/locale/health_lifestyle.pot
trytond/modules/health_lifestyle/locale/it_IT.po
trytond/modules/health_lifestyle/locale/ja_JP.po
trytond/modules/health_lifestyle/locale/ka.po
trytond/modules/health_lifestyle/locale/lo.po
trytond/modules/health_lifestyle/locale/pt_BR.po
trytond/modules/health_lifestyle/locale/sv.po
trytond/modules/health_lifestyle/locale/tr.po
trytond/modules/health_lifestyle/locale/uk.po
trytond/modules/health_lifestyle/locale/vi.po
trytond/modules/health_lifestyle/locale/zh_CN.po
trytond/modules/health_lifestyle/pyproject.toml
trytond/modules/health_lifestyle/security/access_rights.xml
trytond/modules/health_lifestyle/tests/__init__.py
trytond/modules/health_lifestyle/tests/test_health_lifestyle.py
trytond/modules/health_lifestyle/tryton.cfg
trytond/modules/health_lifestyle/view/gnuhealth_diet_belief_form.xml
trytond/modules/health_lifestyle/view/gnuhealth_diet_belief_tree.xml
trytond/modules/health_lifestyle/view/gnuhealth_drugs_recreational.xml
trytond/modules/health_lifestyle/view/gnuhealth_drugs_recreational_tree.xml
trytond/modules/health_lifestyle/view/gnuhealth_patient.xml
trytond/modules/health_lifestyle/view/gnuhealth_patient_cage.xml
trytond/modules/health_lifestyle/view/gnuhealth_patient_cage_tree.xml
gnuhealth_lifestyle-5.0.2.dist-info/METADATA
gnuhealth_lifestyle-5.0.2.dist-info/WHEEL
gnuhealth_lifestyle-5.0.2.dist-info/licenses/COPYING
gnuhealth_lifestyle-5.0.2.dist-info/RECORD
